packer/__init__.py
packer/exceptions.py
packer/packer.py
packer/protocols.py
packer/pack_types/__init__.py
packer/pack_types/base.py
packer/pack_types/float_types.py
packer/pack_types/int_types.py
packer/pack_types/other.py
packer/pack_types/pack_types.py
packer/pack_types/size_defined_types.py
packer/utils/__init__.py
packer/utils/dynamic_helper.py
packer_typed-0.2.7.dist-info/LICENSE
packer_typed-0.2.7.dist-info/METADATA
packer_typed-0.2.7.dist-info/WHEEL
packer_typed-0.2.7.dist-info/top_level.txt
packer_typed-0.2.7.dist-info/RECORD
