Metadata-Version: 2.2
Name: packer.typed
Version: 0.2.7
Summary: A modern library that simplifies packing and unpacking to a whole other level.
License: MIT License
Project-URL: Homepage, https://github.com/biggus-developerus/packer.typed
Project-URL: Bug Tracker, https://github.com/biggus-developerus/packer.typed/issues
Classifier: Programming Language :: Python :: 3.12
Classifier: Programming Language :: Python :: 3.13
Classifier: License :: OSI Approved :: MIT License
Classifier: Operating System :: OS Independent
Requires-Python: >=3.12.0
License-File: LICENSE
